xpynfo/__init__.py
xpynfo/__init__.pyc
xpynfo/poc.py
xpynfo/poc.pyc
xpynfo/__pycache__/__init__.cpython-36.pyc
xpynfo/__pycache__/poc.cpython-36.pyc
xpynfo-0.0.0.dist-info/METADATA
xpynfo-0.0.0.dist-info/RECORD
xpynfo-0.0.0.dist-info/WHEEL
xpynfo-0.0.0.dist-info/entry_points.txt
xpynfo-0.0.0.dist-info/top_level.txt
