Metadata-Version: 2.1
Name: xpynfo
Version: 0.0.0
Summary: A handy, pretty-printing X window metadata CLI
Home-page: https://github.com/wizardsoftheweb/xpynfo#readme
Author: CJ Harries
Author-email: cj@wizardsoftheweb.pro
License: ISC
Project-URL: Issue Tracker, https://github.com/wizardsoftheweb/xpynfo/issues
Keywords: xlib,xcb,xorg
Platform: UNKNOWN
Classifier: Development Status :: 1 - Planning
Classifier: Environment :: Console
Classifier: Environment :: X11 Applications
Requires-Dist: pytest-runner
Requires-Dist: anytree
Requires-Dist: xcffib
